.travis.yml
AUTHORS
ChangeLog
LICENSE
README.md
VERSION
requirements.txt
setup.cfg
setup.py
test-requirements.txt
open_clmcli/clm_client.py
open_clmcli/clm_common.py
open_clmcli/clm_netfunction.py
open_clmcli/clm_repository.py
open_clmcli/clmcli.py
open_clmcli.egg-info/PKG-INFO
open_clmcli.egg-info/SOURCES.txt
open_clmcli.egg-info/dependency_links.txt
open_clmcli.egg-info/entry_points.txt
open_clmcli.egg-info/not-zip-safe
open_clmcli.egg-info/pbr.json
open_clmcli.egg-info/requires.txt
open_clmcli.egg-info/top_level.txt