Metadata-Version: 1.0
Name: open-clmcli
Version: 0.0.2
Summary: CLI for Nokia CLM
Home-page: http://www.github.com/maxiterr/open-clmcli
Author: Maxime Terras
Author-email: mterras@bouyguestelecom.fr
License: MIT
Platform: UNKNOWN
